{"runners":[{"id":"AnigliScans","version":1.04,"name":"AnigliScans","thumbnail":"AnigliScans.png","rating":1,"website":"https://anigliscans.xyz","path":"AnigliScans","environment":"source","hash":"78641b64236a9421023df015255b51fd8f5e01b1ec8b9e2ec066c3ff751f5af7"},{"id":"AresManga","version":1.04,"name":"AresManga","thumbnail":"AresManga.png","rating":1,"website":"https://en-aresmanga.com","path":"AresManga","environment":"source","hash":"75163b4968675ca627467561449305cacbc18c5d97721d5e8c32c01031f6d698"},{"id":"AsuraScans","version":1.04,"name":"AsuraScans","thumbnail":"AsuraScans.png","rating":1,"website":"https://asuratoon.com","path":"AsuraScans","environment":"source","hash":"0f397698c5b9bca56e053940bf3320c2ecfb64fc7d0064f312e11012c9867937"},{"id":"ElarcPage","version":1.04,"name":"ElarcPage","thumbnail":"ElarcPage.png","rating":1,"website":"https://elarctoon.com","path":"ElarcPage","environment":"source","hash":"7d85379121d650b9d1506f71520655c7eca5cc3fe2f4f6e0b71f9ec1cdff40f0"},{"id":"FlameComics","version":1.04,"name":"FlameComics","thumbnail":"FlameComics.png","rating":1,"website":"https://flamecomics.com","path":"FlameComics","environment":"source","hash":"6e4a1a426c87cd87dfdfb91ad4cd838b75da974d22c143aef67259f4850519fc"},{"id":"FreakScans","version":1.04,"name":"FreakScans","thumbnail":"FreakScans.png","rating":1,"website":"https://freakscans.com","path":"FreakScans","environment":"source","hash":"3e03f5a467d95f4f63a0be89bf1350ec9cbdd2a6b0fcf9b175fdfa83f93379c1"},{"id":"HelScans","version":1.04,"name":"HelScans","thumbnail":"HelScans.png","rating":1,"website":"https://helscans.com","path":"HelScans","environment":"source","hash":"5e9ece03e26cfb6c8c1205d6b0fcc963de29078b4f130bc19bf50d2df8a2ef38"},{"id":"Hentai20","version":1.04,"name":"Hentai20","thumbnail":"Hentai20.png","rating":2,"website":"https://hentai20.io","path":"Hentai20","environment":"source","hash":"1ecc1d7b15eecee27d0b2da56510de5a1ad43e805a216be9bf887f48aae45f6e"},{"id":"InfernalVoidScans","version":1.04,"name":"InfernalVoidScans","thumbnail":"InfernalVoidScans.png","rating":1,"website":"https://void-scans.com","path":"InfernalVoidScans","environment":"source","hash":"734876b427a0e447e2aad86dec9ce1368b3640f16dce974e729f4a5da9b8de38"},{"id":"LelManga","version":1.04,"name":"LelManga","thumbnail":"LelManga.png","rating":1,"website":"https://www.lelmanga.com","path":"LelManga","environment":"source","hash":"8fbbfbae929a6556390e24fb5a918871047c5a110122d622c10e9e27fb43640e"},{"id":"LuminousScans","version":1.04,"name":"LuminousScans","thumbnail":"LuminousScans.png","rating":1,"website":"https://lumitoon.com","path":"LuminousScans","environment":"source","hash":"cf7fbbcbe0d976e969693f7bfc70454049d23319a08a5c68fe36e2831c714839"},{"id":"ManhwaX","version":1.04,"name":"ManhwaX","thumbnail":"ManhwaX.png","rating":2,"website":"https://manhwax.org","path":"ManhwaX","environment":"source","hash":"4cde0cb781be69c5fd5e7aa996f528f4c649eb0d5c8473a894df3ba7afb63cad"},{"id":"NightScans","version":1.04,"name":"NightScans","thumbnail":"NightScans.png","rating":1,"website":"https://night-scans.com","path":"NightScans","environment":"source","hash":"906d1ce41b98807934e7c615be0309cf458d0f157cdeeb3501ad306d9eb0094f"},{"id":"QuantumScans","version":1.04,"name":"QuantumScans","thumbnail":"QuantumScans.png","rating":1,"website":"https://readers-point.space","path":"QuantumScans","environment":"source","hash":"481014bce30f4b763c725a8578330c52af410da7b95d192068fb4d3f1d978890"},{"id":"RawKuma","version":1.04,"name":"RawKuma","thumbnail":"RawKuma.png","rating":1,"website":"https://rawkuma.com","path":"RawKuma","environment":"source","hash":"6294ce90b7f05a465f638c2ee97eec23513e591b6a400eaacd3aaa04aa7b0a5b"},{"id":"ReadKomik","version":1.04,"name":"ReadKomik","thumbnail":"ReadKomik.png","rating":1,"website":"https://readkomik.com","path":"ReadKomik","environment":"source","hash":"af9e624c106ddfb50461eb8d6bf6bd89a1d043e454ffa56f0f67cfe361faba40"},{"id":"SkyMangas","version":1.04,"name":"SkyMangas","thumbnail":"SkyMangas.png","rating":1,"website":"https://skymangas.com","path":"SkyMangas","environment":"source","hash":"a2786b5bb5e05b100a34f48b036e12672cab73dffa7a9f31645398cfe94dfaa6"},{"id":"SuryaScans","version":1.04,"name":"SuryaScans","thumbnail":"SuryaScans.png","rating":1,"website":"https://suryatoon.com","path":"SuryaScans","environment":"source","hash":"7dac3e4575c6b5ecc56c5dee55a36bd370af633ee0f94782d0c32c939b7852f6"},{"id":"Sushi Scan","version":1.04,"name":"Sushi Scan","thumbnail":"SushiScan.png","rating":0,"website":"https://sushiscan.net","path":"SushiScan","environment":"source","hash":"950dd9d8918f45fd8e30a66767d57ccdf54d4e8702f3cb3e85610dd7658d37ec"},{"id":"TeamxNovel","version":1.04,"name":"TeamxNovel","thumbnail":"TeamxNovel.png","rating":1,"website":"https://team11x11.com","path":"TeamxNovel","environment":"source","hash":"6ea2a60b7942e8372a2d727e4a4a0223a030bdb7bb65e0744e58cdc2a5380f14"},{"id":"eDoujin","version":1.04,"name":"eDoujin","thumbnail":"eDoujin.png","rating":2,"website":"https://edoujin.net","path":"eDoujin","environment":"source","hash":"6eeee04cfe710552b15097f546075002563d3efb57e01ad461f583c8246105df"},{"id":"xCalibrScans","version":1.04,"name":"xCalibrScans","thumbnail":"xCalibrScans.png","rating":1,"website":"https://xcalibrscans.com","path":"xCalibrScans","environment":"source","hash":"f874a195135f1ca91e05e9eded1c013dadbc646f2a8e53cdd3f8ecd621a0512a"}],"listName":"Seyden | Suwatte - MangaStream Generic (6.0)"}