{"runners":[{"id":"AllPornComic","version":1.04,"name":"AllPornComic","thumbnail":"AllPornComic.png","rating":2,"website":"https://allporncomic.com","path":"AllPornComic","environment":"source","hash":"e2faa83ca60483f4768bda66e3dc166f3d800c95ca80362e70a45a9290a81bd8"},{"id":"AnigliScans","version":1.05,"name":"AnigliScans","thumbnail":"AnigliScans.png","rating":1,"website":"https://anigliscans.xyz","path":"AnigliScans","environment":"source","hash":"405525134af61a4211b4429b605873b5020a5a63dc05941cc6648c251b1e8094"},{"id":"ArthurScan","version":1.04,"name":"ArthurScan","thumbnail":"ArthurScan.png","rating":1,"website":"https://arthurscan.xyz","path":"ArthurScan","environment":"source","hash":"259742d23c945745d3b3b8e1224cd73bcb8ccd7920d7c8027c17d2bdd4bc4be6"},{"id":"ArvenScans","version":1.05,"name":"ArvenScans","thumbnail":"ArvenScans.png","rating":1,"website":"https://arvencomics.com","path":"ArvenScans","environment":"source","hash":"6baef1f5939db3f27f89043bce29e0427d3b2abfa81b7a55ee8307eb970853f8"},{"id":"AstraScans","version":1.05,"name":"AstraScans","thumbnail":"AstraScans.png","rating":1,"website":"https://astrascans.org","path":"AstraScans","environment":"source","hash":"161c71314ff1a0857ff5243dc8b437c1ab21bc7bc85dc583796c03d0941dd4fa"},{"id":"AstralLibrary","version":1.04,"name":"AstralLibrary","thumbnail":"AstralLibrary.png","rating":0,"website":"https://astrallibrary.net","path":"AstralLibrary","environment":"source","hash":"e829b77e261bb848d347973ec35fb33d9d4e7ca8040689f793417c3cb62b7019"},{"id":"AsuraScans","version":2.01,"name":"AsuraScans","thumbnail":"AsuraScans.png","rating":1,"website":"https://asuracomic.net","path":"AsuraScans","environment":"source","hash":"0e9f6b643777abd03d2c34daf01ed1b799f4d549d9cbd321fbbfba081b400363"},{"id":"AzoraWorld","version":1.04,"name":"AzoraWorld","thumbnail":"AzoraWorld.png","rating":1,"website":"https://azoramoon.com","path":"AzoraWorld","environment":"source","hash":"841580f225ae0da669719436aacc61c3475e71736936792abcb48dcbf976ecdf"},{"id":"BibiManga","version":1.04,"name":"BibiManga","thumbnail":"BibiManga.png","rating":0,"website":"https://bibimanga.com","path":"BibiManga","environment":"source","hash":"ea57a535e25e3b4201b4c55f0db0da2ae346d7350baad4fbb45c0a7e14523443"},{"id":"ChibiManga","version":1.04,"name":"ChibiManga","thumbnail":"ChibiManga.png","rating":1,"website":"https://www.cmreader.info","path":"ChibiManga","environment":"source","hash":"695e732b43e9a822bf45dc687b99f34f28f6be352c54880a3dbcb7c69dcfa08b"},{"id":"CoffeeManga","version":1.04,"name":"CoffeeManga","thumbnail":"CoffeeManga.png","rating":1,"website":"https://coffeemanga.io","path":"CoffeeManga","environment":"source","hash":"9d3b9376cd28103667ef98de79d2552f1c56116e362c98e4d4ab075e218b8648"},{"id":"ColoredManga","version":1.04,"name":"ColoredManga","thumbnail":"ColoredManga.png","rating":1,"website":"https://coloredmanga.com","path":"ColoredManga","environment":"source","hash":"8875b5299988609dfc87dedb1f049d5280c83f7cb3e3019945e57345057d5f97"},{"id":"CypherScans","version":1.05,"name":"CypherScans","thumbnail":"CypherScans.png","rating":1,"website":"https://cypherscans.xyz","path":"CypherScans","environment":"source","hash":"f173f49b4bc23e174c39d4ec3b2c13a738d53bfd40bf46ceb63160ebbb1a5f7a"},{"id":"DarkScans","version":1.04,"name":"DarkScans","thumbnail":"DarkScans.png","rating":1,"website":"https://darkscans.com","path":"DarkScans","environment":"source","hash":"d80dd9db5841675e552aa9cfeda890a1f840343f00ce9222ae8decfeccb56c6d"},{"id":"DragonTea","version":1.04,"name":"DragonTea","thumbnail":"DragonTea.png","rating":1,"website":"https://dragontea.ink","path":"DragonTea","environment":"source","hash":"b18ff5c22114cff4480b6c72176ad689596ddc824caaa6ad6fa90b52c00675e3"},{"id":"DrakeScans","version":1.04,"name":"DrakeScans","thumbnail":"DrakeScans.png","rating":0,"website":"https://drakecomic.com","path":"DrakeScans","environment":"source","hash":"ca5e717da447e896f6ab8d4cabd232fd4fb70ed6da3dc5ffaefcb23000e46650"},{"id":"ElarcToon","version":1.05,"name":"ElarcToon","thumbnail":"ElarcToon.png","rating":1,"website":"https://elarctoons.biz","path":"ElarcPage","environment":"source","hash":"e6b015142cb04019b21561fa78e03159faf226be1ddcf0feb72fa12184817ce7"},{"id":"FlameComics","version":1.05,"name":"FlameComics","thumbnail":"FlameComics.png","rating":1,"website":"https://flamecomics.me","path":"FlameComics","environment":"source","hash":"626f8a2f407746b5499d3e92572d13a607c069cca55c1d9bdf31e08a4153d1c2"},{"id":"FreakScans","version":1.05,"name":"FreakScans","thumbnail":"FreakScans.png","rating":1,"website":"https://freakscans.com","path":"FreakScans","environment":"source","hash":"701d4dd9b55cd7f48e6605e72ae703eb08423583b596148336c628d0693480c0"},{"id":"GourmetScans","version":1.04,"name":"GourmetScans","thumbnail":"GourmetScans.png","rating":1,"website":"https://gourmetsupremacy.com","path":"GourmetScans","environment":"source","hash":"68b22085ac21ae5163032a9aba9d6118ac9afa65a9d12aadac592c01a6942f7a"},{"id":"Hentai20","version":1.05,"name":"Hentai20","thumbnail":"Hentai20.png","rating":2,"website":"https://hentai20.io","path":"Hentai20","environment":"source","hash":"f888a1ef87d3f3c09c80499b87032969a714978a74c47ad8130062267eb0fdd0"},{"id":"HiperDex","version":1.04,"name":"HiperDex","thumbnail":"HiperDex.png","rating":2,"website":"https://hiperdex.com","path":"HiperDex","environment":"source","hash":"d08d0e3f37852becd86c53382ec87bac5cb969807641a3a964d1626192e90757"},{"id":"HuntManga","version":1.04,"name":"HuntManga","thumbnail":"HuntManga.png","rating":1,"website":"https://huntmanga.com","path":"HuntManga","environment":"source","hash":"e8bb280b84554e509cc8f86300d9973ee7458cc64ef8e429655ddb264e1c0508"},{"id":"ImmortalUpdates","version":1.04,"name":"ImmortalUpdates","thumbnail":"ImmortalUpdates.png","rating":1,"website":"https://immortalupdates.com","path":"ImmortalUpdates","environment":"source","hash":"d516a525b99ea020469ea074bf334ca6482dcc5bb649dd24e6945ea07258a753"},{"id":"InfernalVoidScans","version":1.05,"name":"InfernalVoidScans","thumbnail":"InfernalVoidScans.png","rating":1,"website":"https://hivetoon.com","path":"InfernalVoidScans","environment":"source","hash":"94f9664e05fab907b8b2222fd772f4adde6f946622761a57fc6ed6656cc8dea2"},{"id":"KissManga","version":1.04,"name":"KissManga","thumbnail":"KissManga.png","rating":1,"website":"https://1st-kissmanga.net","path":"KissManga","environment":"source","hash":"ff5b6201a0c6f22d262216f93956af9b4fe75d027353db1e72a0cca578d55e08"},{"id":"KnightNoScanlation","version":1.04,"name":"KnightNoScanlation","thumbnail":"KnightNoScanlation.png","rating":1,"website":"https://knightnoscanlation.com","path":"KnightNoScanlation","environment":"source","hash":"e29a9e04b2642057df1a028eaf0dd812e4d90e963c01468cdeeaa94d99d0cacf"},{"id":"KunManga","version":1.04,"name":"KunManga","thumbnail":"KunManga.png","rating":0,"website":"https://kunmanga.com","path":"KunManga","environment":"source","hash":"f54ff16710c5d106db440f10b5cf95ded6c70467925f69c8cb190ff2bbe7226f"},{"id":"LHTranslation","version":1.04,"name":"LHTranslation","thumbnail":"LHTranslation.png","rating":0,"website":"https://lhtranslation.net","path":"LHTranslation","environment":"source","hash":"2124ad457ce5068e4efc406241edb3bf217eed22228d1068c63d2a64dacbfd60"},{"id":"LSComic","version":1.04,"name":"LSComic","thumbnail":"LSComic.png","rating":0,"website":"https://lscomic.com","path":"LSComic","environment":"source","hash":"6384c7899cd28b1c6d1de60187c474c92ded251141534e30f1589a167d5b4bda"},{"id":"LelManga","version":1.05,"name":"LelManga","thumbnail":"LelManga.png","rating":1,"website":"https://www.lelmanga.com","path":"LelManga","environment":"source","hash":"1102f121e589461520dea209e2d9edac7139764bcabdfc08f69a56b38e5ba67a"},{"id":"LilyManga","version":1.04,"name":"LilyManga","thumbnail":"LilyManga.png","rating":1,"website":"https://lilymanga.net","path":"LilyManga","environment":"source","hash":"5812b5b14328d47645139657c734cdd5643687c1b89009009203d14e62c000ff"},{"id":"LuaScans","version":1.05,"name":"LuaScans","thumbnail":"LuaScans.png","rating":0,"website":"https://luacomic.net","path":"LuaScans","environment":"source","hash":"32dae48bfb5ad525733de60913d4b5d958ad16c7716d5b82beac7fad7f22252e"},{"id":"LuminousScans","version":1.05,"name":"LuminousScans","thumbnail":"LuminousScans.png","rating":1,"website":"https://luminous-scans.com","path":"LuminousScans","environment":"source","hash":"b4c3503428e6bf9f73adbb4c170eed19abf5302c37bb9e78f7f01c7074b59847"},{"id":"LunarScans","version":1.05,"name":"LunarScans","thumbnail":"LuaScans.png","rating":2,"website":"https://lunarscan.org","path":"LunarScans","environment":"source","hash":"846ea35be3489bd718e7109e42f5aceb6e14dcaa8d45dc177815818e1a045a16"},{"id":"Madaradex","version":1.04,"name":"Madaradex","thumbnail":"Madaradex.png","rating":2,"website":"https://madaradex.org","path":"MadaraDex","environment":"source","hash":"758ca2c6aaa1902f24c1fc4bbbb5804d6037a6c2d17ffd5a0f3834041582d64c"},{"id":"Manga3S","version":1.04,"name":"Manga3S","thumbnail":"Manga3S.png","rating":1,"website":"https://www.manga3s.com","path":"Manga3S","environment":"source","hash":"33b0fc7e5120fb956c3b5e2c8ffad655e88b993160f78dfbee5e2c820db479ae"},{"id":"Manga3asq","version":1.04,"name":"Manga3asq","thumbnail":"Manga3asq.png","rating":1,"website":"https://3asq.org","path":"Manga3asq","environment":"source","hash":"569c480ffae000306b30a30850c3d3965148e17253c28a708d2a8dccd902180c"},{"id":"MangaBob","version":1.04,"name":"MangaBob","thumbnail":"MangaBob.png","rating":0,"website":"https://mangabob.com","path":"MangaBob","environment":"source","hash":"0b972f6be8540742a9a63b4ff6f4682c05a4735f191335b0b9c41ea572d6ad85"},{"id":"MangaClash","version":1.04,"name":"MangaClash","thumbnail":"MangaClash.png","rating":1,"website":"https://mangaclash.com","path":"MangaClash","environment":"source","hash":"a69dc80f241df1947eaa0b414215f77c191e43eb07a94eae13a0df41504a559b"},{"id":"MangaCultivator","version":1.04,"name":"MangaCultivator","thumbnail":"MangaCultivator.png","rating":0,"website":"https://mangacult.org","path":"MangaCultivator","environment":"source","hash":"903a94e99cfc60d9c6dca096a7755f09c211d36194c75b4e223a8ebcd10f5b66"},{"id":"MangaLek","version":1.04,"name":"MangaLek","thumbnail":"MangaLek.png","rating":1,"website":"https://mangaleku.com","path":"MangaLek","environment":"source","hash":"0019ff09d539890fa13fc4157e289db37331613683b8c2251c2e7bc77e050889"},{"id":"MangaReadOrg","version":1.04,"name":"MangaReadOrg","thumbnail":"MangaReadOrg.png","rating":0,"website":"https://www.mangaread.org","path":"MangaReadOrg","environment":"source","hash":"b3999458e494b805daa55b6f3fbc78a795f88e21701b3962da0a0607f8b46b69"},{"id":"MangaScantrad","version":1.04,"name":"MangaScantrad","thumbnail":"MangaScantrad.png","rating":1,"website":"https://manga-scantrad.io","path":"MangaScantrad","environment":"source","hash":"d25c4470c9807bacc0a8c9c81b8beb89eaaf888eb7619d0e253b80e051d507bf"},{"id":"MangaTX","version":1.04,"name":"MangaTX","thumbnail":"MangaTX.png","rating":1,"website":"https://mangatx.com","path":"MangaTX","environment":"source","hash":"7b517cf65a749f8544b1665692ed73f6d6f265670d3c6604bf8ac15671eb3f5a"},{"id":"ManhuaFast","version":1.04,"name":"ManhuaFast","thumbnail":"ManhuaFast.png","rating":0,"website":"https://manhuafast.com","path":"ManhuaFast","environment":"source","hash":"5181f15c0dff0638c403da2d56e7330f9f68b7825d0049c8fa28a44b037570ca"},{"id":"ManhuaPlus","version":1.04,"name":"ManhuaPlus","thumbnail":"ManhuaPlus.png","rating":0,"website":"https://manhuaplus.com","path":"ManhuaPlus","environment":"source","hash":"859c019ad2b3420dbe27e8e22899c00712ccf74fe2ce72ac69ebf169cf35f2b3"},{"id":"ManhuaSY","version":1.04,"name":"ManhuaSY","thumbnail":"ManhuaSY.png","rating":0,"website":"https://manhuasy.com","path":"ManhuaSY","environment":"source","hash":"1e596a07b886fad1b282501969f6a67a4125328b6d14e6137a2e2640059836bd"},{"id":"Manhuaus","version":1.04,"name":"Manhuaus","thumbnail":"Manhuaus.png","rating":0,"website":"https://manhuaus.com","path":"Manhuaus","environment":"source","hash":"22ac202a09109b27d1ca257e5b85b22bbb10f9a1565a9e61b3617c92ed1f9b27"},{"id":"ManhwaFull","version":1.04,"name":"ManhwaFull","thumbnail":"ManhwaFull.png","rating":1,"website":"https://manhwafull.com","path":"ManhwaFull","environment":"source","hash":"b44fc51c6dca96a4e71a3bb0df4edae29a1216f8ceeaa2a2395e5d9ec9f8c342"},{"id":"ManhwaTop","version":1.04,"name":"ManhwaTop","thumbnail":"ManhwaTop.png","rating":1,"website":"https://manhwatop.com","path":"ManhwaTop","environment":"source","hash":"3612a3b8237aba2641ea0942bb35d77997b8d14e62ca1f10b2dc341da4a4aea2"},{"id":"ManhwaX","version":1.05,"name":"ManhwaX","thumbnail":"ManhwaX.png","rating":2,"website":"https://manhwax.org","path":"ManhwaX","environment":"source","hash":"26d725378fdd0819130d97c608917c92622a319a5d60447a436d45e3612b23a8"},{"id":"NightScans","version":1.05,"name":"NightScans","thumbnail":"NightScans.png","rating":1,"website":"https://night-scans.com","path":"NightScans","environment":"source","hash":"3bd70b9e7a950e34e7cd34374ccdee789f6b62c2c94b5a777988df2377a4ff4f"},{"id":"NovelMic","version":1.04,"name":"NovelMic","thumbnail":"NovelMic.png","rating":1,"website":"https://novelmic.com","path":"NovelMic","environment":"source","hash":"07d9fa57fdd5bc2d5c621ef3abc06c3bc3d0c3f31d140d541613a6ad32213052"},{"id":"PianManga","version":1.04,"name":"PianManga","thumbnail":"PianManga.png","rating":1,"website":"https://pianmanga.me","path":"PianManga","environment":"source","hash":"5a9e4e4c2b94edcc062d80c8c5f986f1adfbbe2905ba28d7e946f003bc8d91b0"},{"id":"PlatinumScans","version":1.04,"name":"PlatinumScans","thumbnail":"PlatinumScans.png","rating":0,"website":"https://platinumscans.com","path":"PlatinumScans","environment":"source","hash":"526b5db818b7e92e043d302e5c92b01dd63e5b2fd95adff7fcb33ad0cef0405d"},{"id":"QuantumScans","version":1.05,"name":"QuantumScans","thumbnail":"QuantumScans.png","rating":1,"website":"https://qscomics.org","path":"QuantumScans","environment":"source","hash":"ced91958c0b78332de45f17a184ecfdac3c6e0f6aaa5aba9aba0cff6fcd1896a"},{"id":"RawKuma","version":1.05,"name":"RawKuma","thumbnail":"RawKuma.png","rating":1,"website":"https://rawkuma.com","path":"RawKuma","environment":"source","hash":"2499dad56b24700284d4e2eacb6f62452b5fe510b2981e274adef4a4cc40ad5f"},{"id":"ReadKomik","version":1.05,"name":"ReadKomik","thumbnail":"ReadKomik.png","rating":1,"website":"https://readkomik.com","path":"ReadKomik","environment":"source","hash":"997414826dddb0d1a91f49bdb62a7fc2363cd19e9fe9e2c8ba4b82343180940d"},{"id":"ReaperScansFR","version":1.04,"name":"ReaperScansFR","thumbnail":"ReaperScansFR.png","rating":0,"website":"https://reaperscans.fr","path":"ReaperScansFR","environment":"source","hash":"f9e32db27314ff31a02ca1a8cbe4d531e204f38793dc8907a4733cc86ee90240"},{"id":"ResetScans","version":1.04,"name":"ResetScans","thumbnail":"ResetScans.png","rating":0,"website":"https://reset-scans.xyz","path":"ResetScans","environment":"source","hash":"096a9cce35181a96d4262d3b448ed7f0a10a0ff8668892e38e3b54e229cd8711"},{"id":"SamuraiScan","version":1.04,"name":"SamuraiScan","thumbnail":"SamuraiScan.png","rating":2,"website":"https://samuraiscan.com","path":"SamuraiScan","environment":"source","hash":"cf53b0e21c13c98ec33c64b34f560e430183d74e554bef19fd204f78e0a79330"},{"id":"SetsuScans","version":1.04,"name":"SetsuScans","thumbnail":"SetsuScans.png","rating":1,"website":"https://setsuscans.com","path":"SetsuScans","environment":"source","hash":"b572cc189b675327e6263fadc78af3f34495b23bef6bf7d1d41bae12fa7560b7"},{"id":"Sinensis","version":1.04,"name":"Sinensis","thumbnail":"Sinensis.png","rating":1,"website":"https://sinensisscans.com","path":"Sinensis","environment":"source","hash":"0eef72b841e1e68d8cf63a2ec97feb86ab82e34e3d237adb2f9fd459fb29f78a"},{"id":"SkyMangas","version":1.05,"name":"SkyMangas","thumbnail":"SkyMangas.png","rating":1,"website":"https://skymangas.com","path":"SkyMangas","environment":"source","hash":"569afb94cd3648fa88580bd9518e257dbbae20acd38699f222dc59e57f6055be"},{"id":"SuryaScans","version":1.05,"name":"SuryaScans","thumbnail":"SuryaScans.png","rating":1,"website":"https://genztoons.com","path":"SuryaScans","environment":"source","hash":"534665f97ac4c742dd5d44aeca0edf2b2639e493be43c43bec473718dcaaa52e"},{"id":"Sushi Scan","version":1.05,"name":"Sushi Scan","thumbnail":"SushiScan.png","rating":0,"website":"https://sushiscan.net","path":"SushiScan","environment":"source","hash":"bc222349fb8bffd99428dfe647932cfbc57735679491e01bc866cd9e89f1c98b"},{"id":"TeamxNovel","version":1.05,"name":"TeamxNovel","thumbnail":"TeamxNovel.png","rating":1,"website":"https://team11x11.com","path":"TeamxNovel","environment":"source","hash":"ad951be658c1374337bcec81d3a8995d801822fcb0537fd28cb653b86c95faa4"},{"id":"TeenManhua","version":1.04,"name":"TeenManhua","thumbnail":"TeenManhua.png","rating":0,"website":"https://teenmanhua.com","path":"TeenManhua","environment":"source","hash":"b4dfad801bbbc3756de3b510dd83e532f6ab50bc997a976bf55444ec074cc554"},{"id":"ToonGod","version":1.04,"name":"ToonGod","thumbnail":"ToonGod.png","rating":2,"website":"https://www.toongod.org","path":"ToonGod","environment":"source","hash":"4bd677ef455dbf53067417bca3f68a21b5bd10104ceae10a2684a3bfa1c31509"},{"id":"Toonily","version":1.04,"name":"Toonily","thumbnail":"Toonily.png","rating":2,"website":"https://toonily.com","path":"Toonily","environment":"source","hash":"e34d5e678fb41ae818dc6f440b0e6b5e267ea6edfe2cecef25b1470da1a7656c"},{"id":"WebtoonXYZ","version":1.04,"name":"WebtoonXYZ","thumbnail":"WebtoonXYZ.png","rating":2,"website":"https://www.webtoon.xyz","path":"WebtoonXYZ","environment":"source","hash":"7d63f479e7e9e9411ad7f71690f7ba759de47101b9353168b5945fd7fd7db480"},{"id":"ZinManga","version":1.04,"name":"ZinManga","thumbnail":"ZinManga.png","rating":1,"website":"https://zinmanga.com","path":"ZinManga","environment":"source","hash":"371b17c7ea0f63d9c6164f571bf4c65afdba5a3594efd84aab70829eaccc4f87"},{"id":"eDoujin","version":1.05,"name":"eDoujin","thumbnail":"eDoujin.png","rating":2,"website":"https://edoujin.net","path":"eDoujin","environment":"source","hash":"76f69b602cac3103b179dd315dfb262eb9f808ff6dda6c7d2a6ec48f21d4426d"},{"id":"xCalibrScans","version":1.05,"name":"xCalibrScans","thumbnail":"xCalibrScans.png","rating":1,"website":"https://xcalibrscans.com","path":"xCalibrScans","environment":"source","hash":"fbb5fb3ef769de0a6e12753bcf68a5bd1e2f7ceff8bd7fafddc16bc58cc5b889"}],"listName":"Seyden | Suwatte - Generic (6.0)"}