{"runners":[{"id":"AllPornComic","version":1.04,"name":"AllPornComic","thumbnail":"AllPornComic.png","rating":2,"website":"https://allporncomic.com","path":"AllPornComic","environment":"source","hash":"90f19a9c0d696ad44998b72b7ec759c17796fbad0000a201290cef01ed8d2c0c"},{"id":"AnigliScans","version":1.05,"name":"AnigliScans","thumbnail":"AnigliScans.png","rating":1,"website":"https://anigliscans.xyz","path":"AnigliScans","environment":"source","hash":"c4cdffe101ad8bab6db2bc9bd8afcbf05f0c6b836d59d54e6deb0a690acc82a1"},{"id":"ArthurScan","version":1.04,"name":"ArthurScan","thumbnail":"ArthurScan.png","rating":1,"website":"https://arthurscan.xyz","path":"ArthurScan","environment":"source","hash":"f6bd8fb45e6c117c090647f07a815920bab03cbe5b7f42d6e5e7ba5f83a0ce3e"},{"id":"ArvenScans","version":1.05,"name":"ArvenScans","thumbnail":"ArvenScans.png","rating":1,"website":"https://arvencomics.com","path":"ArvenScans","environment":"source","hash":"8d78935fb2e38fb65922da23ec7c5593571651fd03b4cafe677a471954627bb0"},{"id":"AstraScans","version":1.05,"name":"AstraScans","thumbnail":"AstraScans.png","rating":1,"website":"https://astrascans.org","path":"AstraScans","environment":"source","hash":"d3cca26ccc0ce0c063489ecc80c8c7621423efeefff5683864256d643e9c75b2"},{"id":"AstralLibrary","version":1.04,"name":"AstralLibrary","thumbnail":"AstralLibrary.png","rating":0,"website":"https://astrallibrary.net","path":"AstralLibrary","environment":"source","hash":"7ecede9076eb27af73fae160ec827502c27b79f39e896d7b21150d1b87160edc"},{"id":"AsuraScans","version":2.1,"name":"AsuraScans","thumbnail":"AsuraScans.png","rating":1,"website":"https://asuracomic.net","path":"AsuraScans","environment":"source","hash":"6d03c4f549d8e9457eeb044b3d010a0258b006593795cc39b4bf187d9a65a9f7"},{"id":"AzoraWorld","version":1.04,"name":"AzoraWorld","thumbnail":"AzoraWorld.png","rating":1,"website":"https://azoramoon.com","path":"AzoraWorld","environment":"source","hash":"82da557a40e6c6096d01f7fa3e93033b341235d77cd28001bd2aed9e31d30701"},{"id":"BibiManga","version":1.04,"name":"BibiManga","thumbnail":"BibiManga.png","rating":0,"website":"https://bibimanga.com","path":"BibiManga","environment":"source","hash":"d6b07e07544d595c4912130ce3102987dd575aed81d53de767952e14946bd8f4"},{"id":"ChibiManga","version":1.04,"name":"ChibiManga","thumbnail":"ChibiManga.png","rating":1,"website":"https://www.cmreader.info","path":"ChibiManga","environment":"source","hash":"fddbfe39986130d48affca25cfa4b74f9721999ac9d665e752e7d1e9a024c0e0"},{"id":"CoffeeManga","version":1.04,"name":"CoffeeManga","thumbnail":"CoffeeManga.png","rating":1,"website":"https://coffeemanga.io","path":"CoffeeManga","environment":"source","hash":"e20abd61ba614029dfe029bf0604e97a7643c4d5edafd035f22b94dead0e4401"},{"id":"ColoredManga","version":1.04,"name":"ColoredManga","thumbnail":"ColoredManga.png","rating":1,"website":"https://coloredmanga.com","path":"ColoredManga","environment":"source","hash":"8e81add3085720825f1ebd7390db750a18c5ca10e0199a9068a817bf7597de38"},{"id":"CypherScans","version":1.05,"name":"CypherScans","thumbnail":"CypherScans.png","rating":1,"website":"https://cypherscans.xyz","path":"CypherScans","environment":"source","hash":"ab342dffd11f250add310a106dcf1c094b381d7acc4267a5cf830c53d15d40b4"},{"id":"DarkScans","version":1.04,"name":"DarkScans","thumbnail":"DarkScans.png","rating":1,"website":"https://darkscans.com","path":"DarkScans","environment":"source","hash":"ea4d9586c93427aeb35b5298ce7ead7700a0e4470b2de7d12fa244f828010336"},{"id":"DragonTea","version":1.04,"name":"DragonTea","thumbnail":"DragonTea.png","rating":1,"website":"https://dragontea.ink","path":"DragonTea","environment":"source","hash":"4206d358a54e60e09b13a8da97bab9917b85c73274ec8c76ecf3c388b23bc562"},{"id":"DrakeScans","version":1.04,"name":"DrakeScans","thumbnail":"DrakeScans.png","rating":0,"website":"https://drakecomic.com","path":"DrakeScans","environment":"source","hash":"fbb81b78ac84b66f567179df0b23c1e82d7034a61d68e6e58a25fca989de0ee1"},{"id":"ElarcToon","version":1.05,"name":"ElarcToon","thumbnail":"ElarcToon.png","rating":1,"website":"https://elarctoons.biz","path":"ElarcPage","environment":"source","hash":"a94c34f8486d2f246d482fc700042be8a0988dd1307f0c8a278d2a2c8bd4445f"},{"id":"FlameComics","version":1.05,"name":"FlameComics","thumbnail":"FlameComics.png","rating":1,"website":"https://flamecomics.me","path":"FlameComics","environment":"source","hash":"ff1b072820757ccbc46b4c80b66b183da7615f494e87542dafeaedbcf566024f"},{"id":"FreakScans","version":1.05,"name":"FreakScans","thumbnail":"FreakScans.png","rating":1,"website":"https://freakscans.com","path":"FreakScans","environment":"source","hash":"77be7348830ae11f1d2ba9215589cbc23b49c6d029ad54fdd08e14a2e005c65b"},{"id":"GourmetScans","version":1.04,"name":"GourmetScans","thumbnail":"GourmetScans.png","rating":1,"website":"https://gourmetsupremacy.com","path":"GourmetScans","environment":"source","hash":"16a5e2c478d24d842dffd2c0497c0e148e21aea0c1aae8480236ce36c2b691d6"},{"id":"Hentai20","version":1.05,"name":"Hentai20","thumbnail":"Hentai20.png","rating":2,"website":"https://hentai20.io","path":"Hentai20","environment":"source","hash":"b2b26626fa2efef6ad8a8a88af871b4ed4c21aa998bcdb13cf6c671333d56c1f"},{"id":"HiperDex","version":1.04,"name":"HiperDex","thumbnail":"HiperDex.png","rating":2,"website":"https://hiperdex.com","path":"HiperDex","environment":"source","hash":"ca0f9573d3e0465a1519ede55200cd0a6fc960195de8893047e225b68fba97c0"},{"id":"HuntManga","version":1.04,"name":"HuntManga","thumbnail":"HuntManga.png","rating":1,"website":"https://huntmanga.com","path":"HuntManga","environment":"source","hash":"fd53cd72658102af5945d072f2d0d140d3e8fd3e385c9c025b69eab2c1ea5a7d"},{"id":"ImmortalUpdates","version":1.04,"name":"ImmortalUpdates","thumbnail":"ImmortalUpdates.png","rating":1,"website":"https://immortalupdates.com","path":"ImmortalUpdates","environment":"source","hash":"114a4e3bcb1ed7ca2dcc67225822e0e5231aa3599db4fed2fddea4cd33289e5b"},{"id":"InfernalVoidScans","version":1.05,"name":"InfernalVoidScans","thumbnail":"InfernalVoidScans.png","rating":1,"website":"https://hivetoon.com","path":"InfernalVoidScans","environment":"source","hash":"7f6183a682a68a73897a75df10e7dc8fc78b62b268a71ffc73aec9787c828c9f"},{"id":"KissManga","version":1.04,"name":"KissManga","thumbnail":"KissManga.png","rating":1,"website":"https://1st-kissmanga.net","path":"KissManga","environment":"source","hash":"c0aa403f96c607efa9950371560171ba1daae5e969d006239bc1c14b69a45911"},{"id":"KnightNoScanlation","version":1.04,"name":"KnightNoScanlation","thumbnail":"KnightNoScanlation.png","rating":1,"website":"https://knightnoscanlation.com","path":"KnightNoScanlation","environment":"source","hash":"572ff2dcd252e6380e5cea82499a4a43dc52ab538de7bb2d7a825b4d1d6730a9"},{"id":"KunManga","version":1.04,"name":"KunManga","thumbnail":"KunManga.png","rating":0,"website":"https://kunmanga.com","path":"KunManga","environment":"source","hash":"883be2c4a49b9b25965959ff13dd1111d9a72750814474af57a52ab47629cc2d"},{"id":"LHTranslation","version":1.04,"name":"LHTranslation","thumbnail":"LHTranslation.png","rating":0,"website":"https://lhtranslation.net","path":"LHTranslation","environment":"source","hash":"136e8fc9fb6296b87423feea537579ecd2cc93cc47ad72c09ae543e54b0fb854"},{"id":"LSComic","version":1.04,"name":"LSComic","thumbnail":"LSComic.png","rating":0,"website":"https://lscomic.com","path":"LSComic","environment":"source","hash":"571a3b587b442b1f5defda1d98204b6db3850da76f978b0dc1ee06cbfacfaff8"},{"id":"LelManga","version":1.05,"name":"LelManga","thumbnail":"LelManga.png","rating":1,"website":"https://www.lelmanga.com","path":"LelManga","environment":"source","hash":"cb98c8ad7b1bfa292ebd611dd06f648cd332921fc0f50ef07f67d313e228d83c"},{"id":"LilyManga","version":1.04,"name":"LilyManga","thumbnail":"LilyManga.png","rating":1,"website":"https://lilymanga.net","path":"LilyManga","environment":"source","hash":"4502c1175d41c897af3c1babefa36390b1725c0ab1fe249e717bf7cffa197f7a"},{"id":"LuaScans","version":1.05,"name":"LuaScans","thumbnail":"LuaScans.png","rating":0,"website":"https://luacomic.net","path":"LuaScans","environment":"source","hash":"3b90737bf06bfe3e3b1929a6cb028aa8c6602e18b3e0a7029a9cf598324a9a89"},{"id":"LuminousScans","version":1.05,"name":"LuminousScans","thumbnail":"LuminousScans.png","rating":1,"website":"https://luminous-scans.com","path":"LuminousScans","environment":"source","hash":"073b4902e3d8ff304de559facf9bfed4db5b9e0f15d9a67d99183b385b37bf28"},{"id":"LunarScans","version":1.05,"name":"LunarScans","thumbnail":"LuaScans.png","rating":2,"website":"https://lunarscan.org","path":"LunarScans","environment":"source","hash":"003a94dddb4ad09228b8be32c250eb0a61f48608715f60a833054f3c6a78fa8f"},{"id":"Madaradex","version":1.04,"name":"Madaradex","thumbnail":"Madaradex.png","rating":2,"website":"https://madaradex.org","path":"MadaraDex","environment":"source","hash":"18d7415a936d1d08e1cdb93d4a21ee9ba8f13be6e99927531d389da29a4c9ada"},{"id":"Manga3S","version":1.04,"name":"Manga3S","thumbnail":"Manga3S.png","rating":1,"website":"https://www.manga3s.com","path":"Manga3S","environment":"source","hash":"c2835b24a1cd991a7ba144dcc103c093331fce48485f3c8fd391affe75edeb5b"},{"id":"Manga3asq","version":1.04,"name":"Manga3asq","thumbnail":"Manga3asq.png","rating":1,"website":"https://3asq.org","path":"Manga3asq","environment":"source","hash":"ae67050634b78d68ea6790340b66c107a061262f4afc3690f6aac7bf2eb1e44d"},{"id":"MangaBob","version":1.04,"name":"MangaBob","thumbnail":"MangaBob.png","rating":0,"website":"https://mangabob.com","path":"MangaBob","environment":"source","hash":"d4a78f2c1a3227cb980b34677ecde1dbe25e05050962bdf9463889e2b7321f46"},{"id":"MangaClash","version":1.04,"name":"MangaClash","thumbnail":"MangaClash.png","rating":1,"website":"https://mangaclash.com","path":"MangaClash","environment":"source","hash":"e5549a833b2b90fc5db70a46e173320a6d0204fa3f6f7dcb1a258f2cacdaaebb"},{"id":"MangaCultivator","version":1.04,"name":"MangaCultivator","thumbnail":"MangaCultivator.png","rating":0,"website":"https://mangacult.org","path":"MangaCultivator","environment":"source","hash":"d16b7c96e82e4e1a63c8c9a992679eb86ee0c337de433355fc2c7535b3f3007c"},{"id":"MangaLek","version":1.04,"name":"MangaLek","thumbnail":"MangaLek.png","rating":1,"website":"https://mangaleku.com","path":"MangaLek","environment":"source","hash":"d63fa773d97548cf123e77c05a80de8580e99e12681e409e38bd9460328e26b6"},{"id":"MangaReadOrg","version":1.04,"name":"MangaReadOrg","thumbnail":"MangaReadOrg.png","rating":0,"website":"https://www.mangaread.org","path":"MangaReadOrg","environment":"source","hash":"db05ec69b0484ce57bdfff489613c445183504987ac021c426441d84f5936e5d"},{"id":"MangaScantrad","version":1.04,"name":"MangaScantrad","thumbnail":"MangaScantrad.png","rating":1,"website":"https://manga-scantrad.io","path":"MangaScantrad","environment":"source","hash":"2b1d22cfac8da4fd325782030bf0f09b18e7fb489aabd48ee36f815e185e6666"},{"id":"MangaTX","version":1.04,"name":"MangaTX","thumbnail":"MangaTX.png","rating":1,"website":"https://mangatx.com","path":"MangaTX","environment":"source","hash":"1211e4f93919037b9e4e925f34741d573eba26f4d28d55742c4470d3649948b7"},{"id":"ManhuaFast","version":1.04,"name":"ManhuaFast","thumbnail":"ManhuaFast.png","rating":0,"website":"https://manhuafast.com","path":"ManhuaFast","environment":"source","hash":"4fae1197eb4bb8c7824f5e04695beeb6027eba612d3c3e9e72469253b9f36401"},{"id":"ManhuaPlus","version":1.04,"name":"ManhuaPlus","thumbnail":"ManhuaPlus.png","rating":0,"website":"https://manhuaplus.com","path":"ManhuaPlus","environment":"source","hash":"d0a607c6db5f62c2cdeabca6021489610f47f1f86aa38cfe2097817404cb923a"},{"id":"ManhuaSY","version":1.04,"name":"ManhuaSY","thumbnail":"ManhuaSY.png","rating":0,"website":"https://manhuasy.com","path":"ManhuaSY","environment":"source","hash":"a36c239ba07a5d87114a175d1fb23c9f43ef6b46fe68736b63f6da7338b120e3"},{"id":"Manhuaus","version":1.04,"name":"Manhuaus","thumbnail":"Manhuaus.png","rating":0,"website":"https://manhuaus.com","path":"Manhuaus","environment":"source","hash":"6e5d6266646b0fc56a7f280e8ea8829aef285a3422beac78a5f8aa67b7c80c32"},{"id":"ManhwaFull","version":1.04,"name":"ManhwaFull","thumbnail":"ManhwaFull.png","rating":1,"website":"https://manhwafull.com","path":"ManhwaFull","environment":"source","hash":"41ed3b1722b5e356282b607c5da60c21d3b6ec3acbcde492f01474f7a0f242c4"},{"id":"ManhwaTop","version":1.04,"name":"ManhwaTop","thumbnail":"ManhwaTop.png","rating":1,"website":"https://manhwatop.com","path":"ManhwaTop","environment":"source","hash":"783b8881df4bd2b44119574424a6e02a8e01a8b4fac9277e25325a98c1b4ca6e"},{"id":"ManhwaX","version":1.05,"name":"ManhwaX","thumbnail":"ManhwaX.png","rating":2,"website":"https://manhwax.org","path":"ManhwaX","environment":"source","hash":"b86c34565bbb3223ec3e7ec8cf3d89d346919d5bcc4d18c2129e029e7b9bb8bf"},{"id":"NightScans","version":1.05,"name":"NightScans","thumbnail":"NightScans.png","rating":1,"website":"https://night-scans.com","path":"NightScans","environment":"source","hash":"819a127c387f97d653f4a924b6e0cc64edd2af6f1540ce768afba3b4352e4c8e"},{"id":"NovelMic","version":1.04,"name":"NovelMic","thumbnail":"NovelMic.png","rating":1,"website":"https://novelmic.com","path":"NovelMic","environment":"source","hash":"76472a17a36e6847287b326b4b0d6421acc0b1171a26a655a4ebf4c35297f2dd"},{"id":"PianManga","version":1.04,"name":"PianManga","thumbnail":"PianManga.png","rating":1,"website":"https://pianmanga.me","path":"PianManga","environment":"source","hash":"cb98f365cc1d9cdb1a3e3c821d0873f3eb0941baf6a0a5587445371ef20b73ba"},{"id":"PlatinumScans","version":1.04,"name":"PlatinumScans","thumbnail":"PlatinumScans.png","rating":0,"website":"https://platinumscans.com","path":"PlatinumScans","environment":"source","hash":"f5298820723c9760f135fc5d953f8cc8164ca54c304c6fc2ea3e0f5e08b81ed9"},{"id":"QuantumScans","version":1.05,"name":"QuantumScans","thumbnail":"QuantumScans.png","rating":1,"website":"https://qscomics.org","path":"QuantumScans","environment":"source","hash":"2eb606f67342e571588a8059a6e6d9d83af5ce77fabd796dc7789c201215f018"},{"id":"RawKuma","version":1.05,"name":"RawKuma","thumbnail":"RawKuma.png","rating":1,"website":"https://rawkuma.com","path":"RawKuma","environment":"source","hash":"0769dc9103b01c4e5340d3f7b6e1a0eb4a3f3fd42915c41b293e458f5810b3d6"},{"id":"ReadKomik","version":1.05,"name":"ReadKomik","thumbnail":"ReadKomik.png","rating":1,"website":"https://readkomik.com","path":"ReadKomik","environment":"source","hash":"ec8a846b7d2fcf064a21e9cbb6e341a3cdfe580b4d80ecb8362bcc6877e08171"},{"id":"ReaperScansFR","version":1.04,"name":"ReaperScansFR","thumbnail":"ReaperScansFR.png","rating":0,"website":"https://reaperscans.fr","path":"ReaperScansFR","environment":"source","hash":"65c40bc9c58f0d691734794a5d527aa074716c6f129bd3ff6a0ecdd62f17273c"},{"id":"ResetScans","version":1.04,"name":"ResetScans","thumbnail":"ResetScans.png","rating":0,"website":"https://reset-scans.xyz","path":"ResetScans","environment":"source","hash":"eede8a0fb0f4ee8ceb7f6e78df73378a1d482c765b1f13246daadd7eed0a2f1b"},{"id":"SamuraiScan","version":1.04,"name":"SamuraiScan","thumbnail":"SamuraiScan.png","rating":2,"website":"https://samuraiscan.com","path":"SamuraiScan","environment":"source","hash":"e214e2e4c0fcc79b1884d0e57a9729b41ab71e2415af530c792fc3ac469b3cbf"},{"id":"SetsuScans","version":1.04,"name":"SetsuScans","thumbnail":"SetsuScans.png","rating":1,"website":"https://setsuscans.com","path":"SetsuScans","environment":"source","hash":"32e8dadb0bfd4c0df87f8cffea38178f4728f23214eccef6e3b8a0e3bf6a90e0"},{"id":"Sinensis","version":1.04,"name":"Sinensis","thumbnail":"Sinensis.png","rating":1,"website":"https://sinensisscans.com","path":"Sinensis","environment":"source","hash":"7da4622d0bba2be6f1e0a4e515a970d45fa77c82314bde216602f08a8ea087f4"},{"id":"SkyMangas","version":1.05,"name":"SkyMangas","thumbnail":"SkyMangas.png","rating":1,"website":"https://skymangas.com","path":"SkyMangas","environment":"source","hash":"729e0d837ac926ef1878078f1a0f78c2d029c21c5298402f85686e184f72e8bd"},{"id":"SuryaScans","version":1.05,"name":"SuryaScans","thumbnail":"SuryaScans.png","rating":1,"website":"https://genztoons.com","path":"SuryaScans","environment":"source","hash":"8dd752f7c2df9f7aaf331d06a1ee6b9b111e0da88941aef2a806913577b03902"},{"id":"Sushi Scan","version":1.05,"name":"Sushi Scan","thumbnail":"SushiScan.png","rating":0,"website":"https://sushiscan.net","path":"SushiScan","environment":"source","hash":"f1a3ac05219f54262d042932ec00e11dc72e7d27f972265d64f1d6211cccb8bf"},{"id":"TeamxNovel","version":1.05,"name":"TeamxNovel","thumbnail":"TeamxNovel.png","rating":1,"website":"https://team11x11.com","path":"TeamxNovel","environment":"source","hash":"fa1835564732cc0a2ca091070b4af559056306407bdfe0b948e62154d6163407"},{"id":"TeenManhua","version":1.04,"name":"TeenManhua","thumbnail":"TeenManhua.png","rating":0,"website":"https://teenmanhua.com","path":"TeenManhua","environment":"source","hash":"80da57994b2cc9636b9a9d8695fd8d77cfa8cf306479b26fadd0f899407a4949"},{"id":"ToonGod","version":1.04,"name":"ToonGod","thumbnail":"ToonGod.png","rating":2,"website":"https://www.toongod.org","path":"ToonGod","environment":"source","hash":"9cbe32892a38519d8a0b33fb8d0068d29a05c605c3336bef21573423cf2b1a8e"},{"id":"Toonily","version":1.04,"name":"Toonily","thumbnail":"Toonily.png","rating":2,"website":"https://toonily.com","path":"Toonily","environment":"source","hash":"7297c45cc24dc339e9b2fcfaa4d6d0dbcab6ac9dd5260318136acdb2b088ec00"},{"id":"WebtoonXYZ","version":1.04,"name":"WebtoonXYZ","thumbnail":"WebtoonXYZ.png","rating":2,"website":"https://www.webtoon.xyz","path":"WebtoonXYZ","environment":"source","hash":"74c64e275fdd625b6571a902a211bb9c425c50e648983d2b12aff44c44862fd9"},{"id":"ZinManga","version":1.04,"name":"ZinManga","thumbnail":"ZinManga.png","rating":1,"website":"https://zinmanga.com","path":"ZinManga","environment":"source","hash":"2db31edb0b191b0945868881b066ba6107cff7cc87ea863a24d423405895a6c0"},{"id":"eDoujin","version":1.05,"name":"eDoujin","thumbnail":"eDoujin.png","rating":2,"website":"https://edoujin.net","path":"eDoujin","environment":"source","hash":"95f0c7c55dfbf8f0dace1ae222167675011cd586c65328cc852fa0cd4512bff1"},{"id":"xCalibrScans","version":1.05,"name":"xCalibrScans","thumbnail":"xCalibrScans.png","rating":1,"website":"https://xcalibrscans.com","path":"xCalibrScans","environment":"source","hash":"311ce74688f9ea21e00bd430c39c97ee7417894fe661b8c8db2f5f5c239a182a"}],"listName":"Seyden | Suwatte - Generic (6.0)"}